README.md
setup.cfg
setup.py
torchinterp1d/__init__.py
torchinterp1d/interp1d.py
torchinterp1d.egg-info/PKG-INFO
torchinterp1d.egg-info/SOURCES.txt
torchinterp1d.egg-info/dependency_links.txt
torchinterp1d.egg-info/requires.txt
torchinterp1d.egg-info/top_level.txt