Metadata-Version: 2.1
Name: torchinterp1d
Version: 1.1
Summary: An interp1d implementation for pytorch
Home-page: https://github.com/aliutkus/torchinterp1d
Author: Antoine Liutkus
Author-email: antoine.liutkus@inria.fr
License: UNKNOWN
Download-URL: https://github.com/aliutkus/torchinterp1d/archive/refs/tags/v1.tar.gz
Keywords: interp1d torch
Platform: UNKNOWN
